[{"type":"player","bot":false,"respawn":false,"name":"[Rus]heroy_105","id":"244501248861011968","maxHealth":100,"health":100,"spawnPoint":"центральная-площадь","location":"центральная-площадь","concentration":50,"target":null,"damage":5,"aggression":0},{"type":"player","bot":false,"respawn":false,"name":"ЧЕФИР","id":"538213290250338306","maxHealth":100,"health":100,"spawnPoint":"центральная-площадь","location":"центральная-площадь","concentration":50,"target":null,"damage":5,"aggression":0},{"type":"player","bot":false,"respawn":false,"name":"·•ROUTER•·","id":"538254799569813504","maxHealth":100,"health":100,"spawnPoint":"центральная-площадь","location":"центральная-площадь","concentration":50,"target":null,"damage":5,"aggression":0},{"type":"player","bot":false,"respawn":false,"name":"polar4ik","id":"538708173650001933","maxHealth":100,"health":100,"spawnPoint":"центральная-площадь","location":"центральная-площадь","concentration":50,"target":null,"damage":5,"aggression":0},{"type":"player","bot":false,"respawn":false,"name":"Geparrrrda","id":"593182799557689479","maxHealth":100,"health":100,"spawnPoint":"центральная-площадь","location":"центральная-площадь","concentration":50,"target":null,"damage":5,"aggression":0},{"type":"player","bot":false,"respawn":false,"name":"lev43","id":"633732275753844774","maxHealth":100,"health":100,"spawnPoint":"центральная-площадь","location":"центральная-площадь","concentration":50,"target":null,"damage":5,"aggression":0},{"type":"player","bot":false,"respawn":false,"name":"ЭтоНеМоёПредназначение","id":"712706426254131251","maxHealth":100,"health":100,"spawnPoint":"центральная-площадь","location":"центральная-площадь","concentration":50,"target":null,"damage":5,"aggression":0},{"type":"player","bot":false,"respawn":false,"name":"RIPka","id":"743127268154540163","maxHealth":100,"health":100,"spawnPoint":"центральная-площадь","location":"центральная-площадь","concentration":50,"target":null,"damage":5,"aggression":0}]